llmcontext/__init__.py
llmcontext/cli.py
llmcontext/extension.py
llmcontext/generator.py
llmcontext/llmstxt.py
llmcontext/project.py
llmcontext/templates.py
llmcontext/templates/default.project.yaml
llmcontext/templates/domains/data.extension.yaml
llmcontext/templates/domains/game.extension.yaml
llmcontext/templates/domains/web.extension.yaml
llm_txt_generator-0.3.0.dist-info/METADATA
llm_txt_generator-0.3.0.dist-info/WHEEL
llm_txt_generator-0.3.0.dist-info/entry_points.txt
llm_txt_generator-0.3.0.dist-info/licenses/LICENSE
llm_txt_generator-0.3.0.dist-info/RECORD
