Metadata-Version: 2.4
Name: llm-txt-generator
Version: 0.3.0
Summary: 从 YAML 配置生成标准化的 AI 协作规则文档 (llm.txt)
Project-URL: Homepage, https://github.com/flashpoint493/LLMTXTGenerator
Project-URL: Repository, https://github.com/flashpoint493/LLMTXTGenerator
Project-URL: Documentation, https://github.com/flashpoint493/LLMTXTGenerator#readme
Author: LLMContextGenerator Contributors
License-Expression: MIT
License-File: LICENSE
Keywords: ai,collaboration,documentation,generator,llm,project-management,vibe-development,yaml
Classifier: Development Status :: 4 - Beta
Classifier: Environment :: Console
Classifier: Intended Audience :: Developers
Classifier: License :: OSI Approved :: MIT License
Classifier: Operating System :: OS Independent
Classifier: Programming Language :: Python :: 3
Classifier: Programming Language :: Python :: 3.8
Classifier: Programming Language :: Python :: 3.9
Classifier: Programming Language :: Python :: 3.10
Classifier: Programming Language :: Python :: 3.11
Classifier: Programming Language :: Python :: 3.12
Classifier: Topic :: Software Development :: Code Generators
Classifier: Topic :: Software Development :: Documentation
Requires-Python: >=3.8
Requires-Dist: click>=8.0
Requires-Dist: pyyaml>=6.0
Requires-Dist: rich>=13.0
Provides-Extra: dev
Requires-Dist: black>=23.0; extra == 'dev'
Requires-Dist: pytest-cov>=4.0; extra == 'dev'
Requires-Dist: pytest>=7.0; extra == 'dev'
Requires-Dist: ruff>=0.1.0; extra == 'dev'
